{"type":"header","name":"t:sections.refactor_words.labels.header_group","sections":{"announcement":{"type":"announcement-bar","blocks":{"content":{"type":"content","settings":{"text":"Svensk köttbutik med hemleverans","link":"","target":false}},"92840699-1b6c-40d5-b7dd-d2fb18917e3b":{"type":"content","settings":{"text":"Snabb hemleverans i hela Sverige","link":"","target":false}},"b4202d17-ebf2-40d8-997a-ca3673a9503c":{"type":"content","settings":{"text":"Fraktfritt över 1. 350:-","link":"","target":false}}},"block_order":["content","92840699-1b6c-40d5-b7dd-d2fb18917e3b","b4202d17-ebf2-40d8-997a-ca3673a9503c"],"settings":{"visibility":"all","show_locale_selector":true,"show_country_selector":true,"show_social_icons":true,"bar_bgcolor":"#111111","bar_txtcolor":"#ffffff"}},"header":{"type":"header","blocks":{"77119bbb-4ea7-4703-bf26-a448c346cceb":{"type":"info","disabled":true,"settings":{"caption":"4.1 på Trustpilot","title":"Mer än 10 000 nöjda kunder","link":"","link_type":"_self","icon":"favorite"}},"info":{"type":"info","settings":{"caption":"Kundservice","title":"0104947730","link":"","link_type":"_self","icon":"helpline"}},"67ef1373-019f-4da4-b05e-5dc78e5ee556":{"type":"mega-menu","settings":{"menu_handle":"produkter","show_promotion_block":true,"promotion_title":"Wagyu kött","promotion_title_size":"text-size--heading","promotion_subtitle":"världens mest kända kött!","promotion_subtitle_size":"text-size--regular","promotion_button_label":"Se mer","promotion_button_size":"regular","promotion_button_link":"shopify:\/\/collections\/wagyu","promotion_color_txt":"#ffffff","promotion_color_bg":"#1d1d1d","promotion_image":"shopify:\/\/shop_images\/Namishi_entreote_2x250g_2048x2048_ae436e08-9353-453d-ab28-14edf06ab2a7.jpg"}},"dd027940-0bf4-413b-8a31-e3a7470ce816":{"type":"mega-menu","settings":{"menu_handle":"inspiration","show_promotion_block":true,"promotion_title":"Premium","promotion_title_size":"text-size--xlarge","promotion_subtitle":"Svensk kött","promotion_subtitle_size":"text-size--regular","promotion_button_label":"Se mer","promotion_button_size":"regular","promotion_button_link":"shopify:\/\/collections\/svensk-kott","promotion_color_txt":"#ffffff","promotion_color_bg":"#1d1d1d","promotion_image":"shopify:\/\/shop_images\/5160-Svenskryggbiff_entrecote.jpg"}},"b279e9e1-72e5-4f4b-aec9-5d5371974ccc":{"type":"mega-menu","settings":{"menu_handle":"köttguide","show_promotion_block":true,"promotion_title":"Great promotion","promotion_title_size":"text-size--xlarge","promotion_subtitle":"Write all about it","promotion_subtitle_size":"text-size--regular","promotion_button_label":"","promotion_button_size":"regular","promotion_button_link":"","promotion_color_txt":"#000000","promotion_color_bg":"#f3f3f3"}},"02ff27b3-9bf0-4a49-9d39-0016fd79ded4":{"type":"store-selector","settings":{}}},"block_order":["77119bbb-4ea7-4703-bf26-a448c346cceb","info","67ef1373-019f-4da4-b05e-5dc78e5ee556","dd027940-0bf4-413b-8a31-e3a7470ce816","b279e9e1-72e5-4f4b-aec9-5d5371974ccc","02ff27b3-9bf0-4a49-9d39-0016fd79ded4"],"settings":{"logo_src":"shopify:\/\/shop_images\/TheFatCow_logo_Black_200x200_3d1f27e8-90f5-4b71-b6ce-f65fec1cf42c.jpg","logo_height":58,"main_linklist":"local-menu","show_search":true,"sticky_header":true,"select_header_actions_on_mobile":"show_always","show_header_actions":true,"show_locale_selector":true,"show_country_selector":true,"show_social_icons":true}}},"order":["announcement","header"]}